Workbook

Sheet Summary
B1: BMC
B2: Expense Book Summary
B3: Sr No | D3: A/c Head | E3: Expense | F3: Expense
B4: 1 | C4: COY Expense | F4: ='COY Expense'!D64 -> 0
B5: 2 | C5: BM CONSTRUCTION PVT LTD | F5: =SUM(E6:E7) -> 0
C6: i | D6: BMC Director Expense | E6: ='BMC Director Expense'!D34 -> 0
C7: ii | D7: BMC Bidding | E7: ='BMC Bidding'!D34 -> 0
B8: 3 | C8: YM CONSTRUCTION | F8: =SUM(E9:E11) -> 0
C9: i | D9: YMC Director Expense | E9: ='YMC Director Expense'!D34 -> 0
C10: ii | D10: YMC Bidding | E10: ='YMC Bidding'!D34 -> 0
C11: iii | D11: C-21, DHA Margala Enclave | E11: ='C-21 DHA Margala'!D31 -> 0
C12: iv | D12: C-21 (A), DHA Margala Enclave | E12: ='C-21 (A) DHA Margala'!D30 -> 2730
B13: 4 | C13: 7-Orbit | F13: =SUM(E14:E15) -> 0
C14: i | D14: 7-Orbit IT | E14: ='7-Orbit IT'!D34 -> 0
C15: ii | D15: 7-Orbit MB | E15: ='7-Orbit MB'!D34 -> 0

Sheet COY Expense
A1: BMC
A2: COY Expense Sheet
A4: Date | B4: Description | C4: A/c | D4: Dr | E4: Cr | F4: Balance
A5: 46235 | B5: Opening Balance | C5: - | D5: 0 | E5: 0 | F5: 0
A6: 46235 | B6: Computer Accessories | C6: Coy Assets | D6: 0 | E6: 0 | F6: =F5-D6+E6 -> 0 | H6: Travelling & Conveyance
A7: 46235 | B7: Attendance Machine for Office | C7: Coy Assets | D7: 0 | E7: 0 | F7: =F6-D7+E7 -> 0 | H7: Printing & Stationary
A8: 46237 | B8: Car Fuel Expense | C8: Director Expense | D8: 0 | E8: 0 | F8: =F7-D8+E8 -> 0 | H8: Entertainment Expense
A9: 46237 | B9: Computer Accessories (Headphone) | C9: Coy Assets | D9: 0 | E9: 0 | F9: =F8-D9+E9 -> 0 | H9: Cleaning Expense
A10: 46237 | B10: Wood Material for Office Workstation | C10: Coy Assets | D10: 0 | E10: 0 | F10: =F9-D10+E10 -> 0 | H10: Utility Expense
A11: 46237 | B11: Paid for Attendance, Wood & Other Exp by Awais Sb | C11: Equity | D11: 0 | E11: 0 | F11: =F10-D11+E11 -> 0 | H11: Coy Assets
A12: 46238 | B12: Advance from Salary to Furqan m/o Aug-26 | C12: Account Receivable | D12: 0 | E12: 0 | F12: =F11-D12+E12 -> 0 | H12: Miscellaneous Expense
A13: 46238 | B13: Paid for Adv Salary Furqan by Awais Sb | C13: Equity | D13: 0 | E13: 0 | F13: =F12-D13+E13 -> 0 | H13: Legal & Professional
A14: 46239 | B14: Computer Accessories | C14: Coy Assets | D14: 0 | E14: 0 | F14: =F13-D14+E14 -> 0 | H14: Rental Liabilty
A15: 46239 | B15: Wood Material for Office Wardrobe | C15: Coy Assets | D15: 0 | E15: 0 | F15: =F14-D15+E15 -> 0 | H15: Director Expense
A16: 46239 | B16: TADA Balnce Payable Clear for Raja Abdullah m/o Jul-26 | C16: Payroll | D16: 0 | E16: 0 | F16: =F15-D16+E16 -> 0 | H16: Payroll
A17: 46239 | B17: Paint Material for Office | C17: Repair & Maintenance | D17: 0 | E17: 0 | F17: =F16-D17+E17 -> 0 | H17: Account Receivable
... A21: 46240 | B21: Paid for Adv Salary Furqan by Awais Sb | C21: Equity | D21: 0 | E21: 0 | F21: =F20-D21+E21 -> 0 | H21: Labor Expense
A22: 46242 | B22: Advance from Salary to Raja Abdullah m/o Aug-26 | C22: Account Receivable | D22: 0 | E22: 0 | F22: =F21-D22+E22 -> 0
A23: 46242 | B23: Office Stationary | C23: Printing & Stationary | D23: 0 | E23: 0 | F23: =F22-D23+E23 -> 0
A24: 46242 | B24: Paid for Adv Salary Furqan by Awais Sb | C24: Equity | D24: 0 | E24: 0 | F24: =F23-D24+E24 -> 0
A25: 46244 | B25: Bike Fuel to Furqan | C25: Travelling & Conveyance | D25: 0 | E25: 0 | F25: =F24-D25+E25 -> 0
A26: 46244 | B26: Advance for Company Sign Boards | C26: Legal & Professional | D26: 0 | E26: 0 | F26: =F25-D26+E26 -> 0
A27: 46244 | B27: Bottles Balnce Payable Clear for Aitzaz Ahsan m/o Jul-26 | C27: Payroll | D27: 0 | E27: 0 | F27: =F26-D27+E27 -> 0
A28: 46244 | B28: Advance from Salary to Aitzaz Ahsan m/o Aug-26 | C28: Account Receivable | D28: 0 | E28: 0 | F28: =F27-D28+E28 -> 0
A29: 46244 | B29: Paid for Adv Salary Furqan by Awais Sb | C29: Equity | D29: 0 | E29: 0 | F29: =F28-D29+E29 -> 0
A30: 46244 | B30: Petty Cash Received for Operational Expense | C30: Petty Cash | D30: 0 | E30: 0 | F30: =F29-D30+E30 -> 0
A31: 46244 | B31: Paid for Petty Cash to Accounts by mubashar Sb | C31: Equity | D31: 0 | E31: 0 | F31: =F30-D31+E31 -> 0
D64: =SUM(D5:D63) -> 0 | E64: =SUM(E5:E63) -> 0 | F64: =F5+D64-E64 -> 0

Sheet BMC Director Expense
A1: BMC
A2: Director Expense Sheet
A4: Date | B4: Description | C4: A/c | D4: Dr | E4: Cr | F4: Balance
A5: 46204 | B5: Opening Balance | C5: - | D5: 0 | E5: 0 | F5: 0
D6: 0 | E6: 0 | F6: =F5-D6+E6 -> 0 | H6: Travelling & Conveyance
D7: 0 | E7: 0 | F7: =F6-D7+E7 -> 0 | H7: Mobile & Telephone Expense
F8: =F7-D8+E8 -> 0 | H8: Entertainment & Hospitality
H9: Hotel & Accommodation
H10: Utility Expenses
H11: Miscellaneous Reimbursements
H12: Vehicle Fuel & Maintenance
H13: Salary / Remuneration
H14: Equity
H15: Equity Withdrawl
D34: =SUM(D5:D33) -> 0 | E34: =SUM(E5:E33) -> 0 | F34: =F5+D34-E34 -> 0

Sheet BMC Bidding
A1: BMC
A2: Bidding Expense Sheet
A4: Date | B4: Description | C4: A/c | D4: Dr | E4: Cr | F4: Balance
A5: 46204 | B5: Opening Balance | C5: - | D5: 0 | E5: 0 | F5: 0
F6: =F5-D6+E6 -> 0 | H6: Tender Fee
F7: =F6-D7+E7 -> 0 | H7: Tender Documentation Expense
F8: =F7-D8+E8 -> 0 | H8: Bid Preparation Expense
F9: =F8-D9+E9 -> 0 | H9: Site Visit Expense
H10: Travel & Conveyance
H11: Accommodation
H12: Courier & Dispatch Charges
H13: Bank Charges – Bid Bond
H14: Printing & Stationery – Tender
H15: E-Procurement Registration Fee
H16: Consultancy Charges – Bidding
H17: Miscellaneous Bidding Expenses
H18: Equity
H19: Equity Withdrawl
D34: =SUM(D5:D33) -> 0 | E34: =SUM(E5:E33) -> 0 | F34: =F5+D34-E34 -> 0

Sheet YMC Director Expense
A1: YMC
A2: Director Expense Sheet
A4: Date | B4: Description | C4: A/c | D4: Dr | E4: Cr | F4: Balance
A5: 46204 | B5: Opening Balance | C5: - | D5: 0 | E5: 0 | F5: 0
D6: 0 | E6: 0 | F6: =F5-D6+E6 -> 0 | H6: Travelling & Conveyance
D7: 0 | E7: 0 | F7: =F6-D7+E7 -> 0 | H7: Mobile & Telephone Expense
F8: =F7-D8+E8 -> 0 | H8: Entertainment & Hospitality
H9: Hotel & Accommodation
H10: Utility Expenses
H11: Miscellaneous Reimbursements
H12: Vehicle Fuel & Maintenance
H13: Salary / Remuneration
H14: Equity
H15: Equity Withdrawl
D34: =SUM(D5:D33) -> 0 | E34: =SUM(E5:E33) -> 0 | F34: =F5+D34-E34 -> 0

Sheet YMC Bidding
A1: YMC
A2: Bidding Expense Sheet
A4: Date | B4: Description | C4: A/c | D4: Dr | E4: Cr | F4: Balance
A5: 46204 | B5: Opening Balance | C5: - | D5: 0 | E5: 0 | F5: 0
F6: =F5-D6+E6 -> 0 | H6: Tender Fee
F7: =F6-D7+E7 -> 0 | H7: Tender Documentation Expense
F8: =F7-D8+E8 -> 0 | H8: Bid Preparation Expense
H9: Site Visit Expense
H10: Travel & Conveyance
H11: Accommodation
H12: Courier & Dispatch Charges
H13: Bank Charges – Bid Bond
H14: Printing & Stationery – Tender
H15: E-Procurement Registration Fee
H16: Consultancy Charges – Bidding
H17: Miscellaneous Bidding Expenses
H18: Equity
H19: Equity Withdrawl
D34: =SUM(D5:D33) -> 0 | E34: =SUM(E5:E33) -> 0 | F34: =F5+D34-E34 -> 0

Sheet C-21 DHA Margala
A1: YMC
A2: Project: C-21, DHA Margala Enclave, Islamabad
A4: Date | B4: Description | C4: A/c | D4: Dr | E4: Cr | F4: Balance
A5: 46235 | B5: Opening Balance | C5: - | D5: 0 | E5: 0 | F5: 0 | H5: Project Expenses
A6: 46235 | B6: Bike Fuel for Project Exp | C6: Site Transportation | D6: 0 | E6: 0 | F6: =F5-D6+E6 -> 0 | H6: Cement
A7: 46235 | B7: Table for Site | C7: Site Office | D7: 0 | E7: 0 | F7: =F6-D7+E7 -> 0 | H7: Steel
A8: 46235 | B8: Advance Salary to Guard m/o Aug-26 | C8: Staff Advance | D8: 0 | E8: 0 | F8: =F7-D8+E8 -> 0 | H8: Sand
A9: 46235 | B9: Powerbank for Guard | C9: Site Security | D9: 0 | E9: 0 | F9: =F8-D9+E9 -> 0 | H9: Crush
A10: 46235 | B10: Bike Fuel to Waqas | C10: Site Transportation | D10: 0 | E10: 0 | F10: =F9-D10+E10 -> 0 | H10: Bricks
A11: 46235 | B11: Paid for Project Expense by Awais Sb | C11: Equity | D11: 0 | E11: 0 | F11: =F10-D11+E11 -> 0 | H11: Electrical
A12: 46239 | B12: Car Fuel Expense | C12: Site Transportation | D12: 0 | E12: 0 | F12: =F11-D12+E12 -> 0 | H12: Plumbing
A13: 46239 | B13: Site Office Container Balance Paid | C13: Site Office | D13: 0 | E13: 0 | F13: =F12-D13+E13 -> 0 | H13: Paint
A14: 46239 | B14: Craine Rent for Shifting of 2nd Office Container | C14: Site Transportation | D14: 0 | E14: 0 | F14: =F13-D14+E14 -> 0 | H14: Tiles
A15: 46239 | B15: Paid for Project Expense by Awais Sb | C15: Equity | D15: 0 | E15: 0 | F15: =F14-D15+E15 -> 0 | H15: Labor
A16: 46242 | B16: Site Misc Expense | C16: Misc | D16: 0 | E16: 0 | F16: =F15-D16+E16 -> 0 | H16: Misc
A17: 46242 | B17: Advance Salary to Guard m/o Aug-26 | C17: Staff Advance | D17: 0 | E17: 0 | F17: =F16-D17+E17 -> 0 | H17: Legal Expense
... A24: 46245 | B24: Paid for Project Expense by Awais Sb | C24: Equity | D24: 0 | E24: 0 | F24: =F23-D24+E24 -> 0 | H24: Site Utilities
H25: Site Security
H26: Site Transportation
H27: Staff Salary
H28: Staff Advance
D31: =SUM(D5:D30) -> 0 | E31: =SUM(E5:E30) -> 0 | F31: =F5+D31-E31 -> 0

Sheet C-21 (A) DHA Margala
A1: YMC
A2: Project: C-21 (A), DHA Margala Enclave, Islamabad
A4: Date | B4: Description | C4: A/c | D4: Dr | E4: Cr | F4: Balance
A5: 46235 | B5: Opening Balance | C5: - | D5: 0 | E5: 0 | F5: 0 | H5: Project Expenses
A6: 46242 | B6: Drawing Coppies of Architecture & Structure A3 | C6: Site Office | D6: 2730 | E6: 0 | F6: =F5-D6+E6 -> -2730 | H6: Cement
A7: 46242 | B7: Paid for Project Expense by Awais Sb | C7: Equity | D7: 0 | E7: 2730 | F7: =F6-D7+E7 -> 0 | H7: Steel
F8: =F7-D8+E8 -> 0 | H8: Sand
F9: =F8-D9+E9 -> 0 | H9: Crush
F10: =F9-D10+E10 -> 0 | H10: Bricks
F11: =F10-D11+E11 -> 0 | H11: Electrical
F12: =F11-D12+E12 -> 0 | H12: Plumbing
F13: =F12-D13+E13 -> 0 | H13: Paint
F14: =F13-D14+E14 -> 0 | H14: Tiles
F15: =F14-D15+E15 -> 0 | H15: Labor
F16: =F15-D16+E16 -> 0 | H16: Misc
F17: =F16-D17+E17 -> 0 | H17: Legal Expense
F18: =F17-D18+E18 -> 0 | H18: Equipment Rental
F19: =F18-D19+E19 -> 0 | H19: Excavation
... F27: =F26-D27+E27 -> 0 | H27: Staff Salary
H28: Staff Advance
D30: =SUM(D5:D29) -> 2730 | E30: =SUM(E5:E29) -> 2730 | F30: =F5+D30-E30 -> 0
B35: Finance:_____________________ | D35: Director:___________________

Sheet 7-Orbit IT
A1: BMC
A2: 7-Orbit IT Expense Sheet
A4: Date | B4: Description | C4: A/c | D4: Dr | E4: Cr | F4: Balance
A5: 46235 | B5: Opening Balance | C5: - | D5: 0 | E5: 0 | F5: 0 | H5: Domain Expense
A6: 46237 | B6: Meta Add Charges | C6: Recruitment Advertising Expenses | D6: 0 | F6: =F5-D6+E6 -> 0 | H6: Corporate Branding Expenses
A7: 46237 | B7: Capcut Subscription for Company | C7: Business Operationl Expense | D7: 0 | F7: =F6-D7+E7 -> 0 | H7: Project Marketing Expenses
H8: Recruitment Advertising Expenses
H9: Business Operationl Expense
H10: Payroll
H11: Equity
H12: Equity Withdrawl
D34: =SUM(D5:D33) -> 0 | E34: =SUM(E5:E33) -> 0 | F34: =F5+D34-E34 -> 0

Sheet 7-Orbit MB
A1: BMC
A2: 7-Orbit MB Expense Sheet
A4: Date | B4: Description | C4: A/c | D4: Dr | E4: Cr | F4: Balance
A5: 46235 | B5: Opening Balance | C5: - | D5: 0 | E5: 0 | F5: 0 | H5: Domain Expense
F6: =F5-D6+E6 -> 0 | H6: Payroll
F7: =F6-D7+E7 -> 0 | H7: Equity
H8: Equity Withdrawl
D34: =SUM(D5:D33) -> 0 | E34: =SUM(E5:E33) -> 0 | F34: =F5+D34-E34 -> 0
